spotdesirability/__init__.py
spotdesirability/data_utils.py
spotdesirability/functions/__init__.py
spotdesirability/functions/rsm.py
spotdesirability/plot/__init__.py
spotdesirability/plot/ccd.py
spotdesirability/utils/__init__.py
spotdesirability/utils/desirability.py
spotdesirability-0.0.14.dist-info/licenses/LICENSE
spotdesirability-0.0.14.dist-info/METADATA
spotdesirability-0.0.14.dist-info/WHEEL
spotdesirability-0.0.14.dist-info/top_level.txt
spotdesirability-0.0.14.dist-info/RECORD
