Metadata-Version: 2.4
Name: spotdesirability
Version: 0.0.14
Summary: spotdesirability - a Python package for desirability
Author-email: "T. Bartz-Beielstein" <tbb@bartzundbartz.de>
License-Expression: GPL-2.0
Project-URL: Homepage, https://www.spotseven.de
Project-URL: Issues, https://github.com/sequential-parameter-optimization/spotdesirability/issues
Project-URL: Repository, https://github.com/sequential-parameter-optimization/spotdesirability
Classifier: Programming Language :: Python :: 3.10
Classifier: Programming Language :: Python :: 3.11
Classifier: Programming Language :: Python :: 3.12
Classifier: Programming Language :: Python :: 3.13
Classifier: Operating System :: OS Independent
Requires-Python: >=3.10
License-File: LICENSE
Requires-Dist: build
Requires-Dist: matplotlib
Requires-Dist: mkdocs>=1.6.0
Requires-Dist: mkdocs-material>=9.5.33
Requires-Dist: mkdocstrings-python>=1.10.8
Requires-Dist: mkdocs-exclude>=1.0.2
Requires-Dist: mkdocs-gen-files>=0.5.0
Requires-Dist: mkdocs-literate-nav>=0.6.1
Requires-Dist: mkdocs-section-index>=0.3.9
Requires-Dist: numpy
Requires-Dist: nbformat
Requires-Dist: pandas
Requires-Dist: python-markdown-math
Requires-Dist: scipy
Requires-Dist: seaborn
Requires-Dist: tabulate
Requires-Dist: typing-extensions>=4.0.0
Dynamic: license-file
